authk/__init__.py
authk/_authk.py
authk/_authorized_keys.py
authk/add.py
authk/remove.py
authk-1.0.5.dist-info/entry_points.txt
authk-1.0.5.dist-info/LICENSE.md
authk-1.0.5.dist-info/WHEEL
authk-1.0.5.dist-info/METADATA
authk-1.0.5.dist-info/RECORD
