Metadata-Version: 2.1
Name: authk
Version: 1.0.5
Summary: SSHD Handling Utility
Author-email: BST Labs <bstlabs@caios.io>
Requires-Python: >=3.8
Classifier: License :: OSI Approved :: MIT License
Requires-Dist: dynacli >= 1.0.7
Requires-Dist: sshpubkeys >= 3.3.1
Requires-Dist: black >=22.3.0 ; extra == "dev"
Requires-Dist: pylint >=2.12.2 ; extra == "dev"
Requires-Dist: isort >=5.9.3 ; extra == "dev"
Requires-Dist: autoflake >=1.4 ; extra == "dev"
Requires-Dist: flake8 >=4.0.1 ; extra == "dev"
Requires-Dist: pre-commit >=2.17.0 ; extra == "dev"
Requires-Dist: mkdocs-material >=8.1.2 ; extra == "doc"
Project-URL: Home, https://github.com/bstlabs/authk
Project-URL: Source, https://github.com/bstlabs/py-authk
Provides-Extra: dev
Provides-Extra: doc
